poetorch/__init__.py
poetorch-0.1.0.dist-info/METADATA
poetorch-0.1.0.dist-info/WHEEL
poetorch-0.1.0.dist-info/RECORD
